odoo/addons/fieldservice_mgmtsystem_nonconformity/README.rst
odoo/addons/fieldservice_mgmtsystem_nonconformity/__init__.py
odoo/addons/fieldservice_mgmtsystem_nonconformity/__manifest__.py
odoo/addons/fieldservice_mgmtsystem_nonconformity/i18n/fieldservice_mgmtsystem_nonconformity.pot
odoo/addons/fieldservice_mgmtsystem_nonconformity/i18n/pt_BR.po
odoo/addons/fieldservice_mgmtsystem_nonconformity/models/__init__.py
odoo/addons/fieldservice_mgmtsystem_nonconformity/models/fsm_order.py
odoo/addons/fieldservice_mgmtsystem_nonconformity/models/mgmtsystem_nonconformity.py
odoo/addons/fieldservice_mgmtsystem_nonconformity/readme/CONTRIBUTORS.rst
odoo/addons/fieldservice_mgmtsystem_nonconformity/readme/DESCRIPTION.rst
odoo/addons/fieldservice_mgmtsystem_nonconformity/readme/USAGE.rst
odoo/addons/fieldservice_mgmtsystem_nonconformity/static/description/icon.png
odoo/addons/fieldservice_mgmtsystem_nonconformity/static/description/index.html
odoo/addons/fieldservice_mgmtsystem_nonconformity/views/mgmtsystem_nonconformity.xml
odoo12_addon_fieldservice_mgmtsystem_nonconformity-12.0.1.1.0.dist-info/METADATA
odoo12_addon_fieldservice_mgmtsystem_nonconformity-12.0.1.1.0.dist-info/WHEEL
odoo12_addon_fieldservice_mgmtsystem_nonconformity-12.0.1.1.0.dist-info/top_level.txt
odoo12_addon_fieldservice_mgmtsystem_nonconformity-12.0.1.1.0.dist-info/RECORD
