Metadata-Version: 2.1
Name: odoo12-addon-fieldservice-mgmtsystem-nonconformity
Version: 12.0.1.1.0
Summary: Bridge module between Field Service and Non Conformities
Home-page: https://github.com/OCA/field-service
Author: Escodoo,Odoo Community Association (OCA)
Author-email: support@odoo-community.org
License: AGPL-3
Platform: UNKNOWN
Classifier: Programming Language :: Python
Classifier: Framework :: Odoo
Classifier: License :: OSI Approved :: GNU Affero General Public License v3
Requires-Python: >=3.5
Requires-Dist: odoo12-addon-fieldservice
Requires-Dist: odoo12-addon-mgmtsystem-nonconformity
Requires-Dist: odoo (<12.1dev,>=12.0a)
